VisionRPA/VisionUI.py
VisionRPA-0.1.4.dist-info/METADATA
VisionRPA-0.1.4.dist-info/WHEEL
VisionRPA-0.1.4.dist-info/top_level.txt
VisionRPA-0.1.4.dist-info/RECORD
