Metadata-Version: 2.1
Name: VisionRPA
Version: 0.1.4
Summary: VisionUI is a RPA product, which can be used for differen automation processes
Home-page: UNKNOWN
Author: ExpertVision
Author-email: ayazpk6630@gmail.com
License: UNKNOWN
Platform: UNKNOWN
Classifier: Intended Audience :: Science/Research
Classifier: Operating System :: Microsoft :: Windows
Classifier: Programming Language :: Python :: 3.8
Requires-Dist: MouseInfo (==0.1.3)
Requires-Dist: numpy (==1.19.4)
Requires-Dist: opencv-python (==4.4.0.46)
Requires-Dist: pandas (==1.1.5)
Requires-Dist: Pillow (==8.0.1)
Requires-Dist: PyAutoGUI (==0.9.52)
Requires-Dist: PyGetWindow (==0.0.9)
Requires-Dist: PyMsgBox (==1.0.9)
Requires-Dist: pyperclip (==1.8.1)
Requires-Dist: PyRect (==0.1.4)
Requires-Dist: PyScreeze (==0.1.26)
Requires-Dist: python-dateutil (==2.8.1)
Requires-Dist: PyTweening (==1.0.3)
Requires-Dist: pytz (==2020.4)
Requires-Dist: pywin32 (==300)
Requires-Dist: six (==1.15.0)
